bugscanx/__init__.py
bugscanx/main.py
bugscanx/modules/__init__.py
bugscanx/modules/miscellaneous/__init__.py
bugscanx/modules/miscellaneous/osint.py
bugscanx/modules/miscellaneous/script_help.py
bugscanx/modules/miscellaneous/txt_toolkit.py
bugscanx/modules/scanners/__init__.py
bugscanx/modules/scanners/host_checker.py
bugscanx/modules/scanners/ip_scan.py
bugscanx/modules/scanners/open_port.py
bugscanx/modules/scanners/sub_scan.py
bugscanx/modules/scrappers/__init__.py
bugscanx/modules/scrappers/dns_info.py
bugscanx/modules/scrappers/ip_lookup.py
bugscanx/modules/scrappers/sub_finder.py
bugscanx/modules/utils/__init__.py
bugscanx/modules/utils/glance.py
bugscanx/modules/utils/handler.py
bugscanx/modules/utils/http_utils.py
bugscanx/modules/utils/necessary.py
bugscanx/modules/utils/other.py
bugscanx/modules/utils/utils.py
ScanBugX-1.3.4.dist-info/LICENSE
ScanBugX-1.3.4.dist-info/METADATA
ScanBugX-1.3.4.dist-info/WHEEL
ScanBugX-1.3.4.dist-info/entry_points.txt
ScanBugX-1.3.4.dist-info/top_level.txt
ScanBugX-1.3.4.dist-info/RECORD
