Metadata-Version: 2.1
Name: ScanBugX
Version: 1.3.4
Summary: All in one toolkit for network analysis
Home-page: https://github.com/ayanrajpoot10/BugScanX
Author: Ayan Rajpoot
Author-email: ayanrajpoot2004@gmail.com
License: MIT
Classifier: Programming Language :: Python :: 3
Classifier: License :: OSI Approved :: MIT License
Classifier: Operating System :: OS Independent
Requires-Python: >=3.6
License-File: LICENSE
